verysimplemodule-anna/__init__.py
verysimplemodule-anna/add.py
verysimplemodule-anna/subtract.py
verysimplemodule-anna/extra/__init__.py
verysimplemodule-anna/extra/divide.py
verysimplemodule-anna/extra/multiply.py
verysimplemodule_anna/__init__.py
verysimplemodule_anna/add.py
verysimplemodule_anna/subtract.py
verysimplemodule_anna/extra/__init__.py
verysimplemodule_anna/extra/divide.py
verysimplemodule_anna/extra/multiply.py
verysimplemodule_annagodoy-0.0.5.dist-info/METADATA
verysimplemodule_annagodoy-0.0.5.dist-info/WHEEL
verysimplemodule_annagodoy-0.0.5.dist-info/top_level.txt
verysimplemodule_annagodoy-0.0.5.dist-info/RECORD
